goombay/__init__.py
goombay/benchmarks.py
goombay/utils.py
goombay/align/__init__.py
goombay/align/base.py
goombay/align/edit.py
goombay/align/edit_msa.py
goombay/align/overlap.py
goombay/align/overlap_msa.py
goombay/phylo/__init__.py
goombay/phylo/cluster.py
goombay-0.24.10.dist-info/METADATA
goombay-0.24.10.dist-info/WHEEL
goombay-0.24.10.dist-info/licenses/LICENSE
goombay-0.24.10.dist-info/RECORD
