Metadata-Version: 2.4
Name: goombay
Version: 0.24.10
Summary: Python implementation of several local, global, and multiple sequence alignment algorithms intended to calculate distance, show alignment, and display the underlying matrices.
Project-URL: Homepage, https://github.com/lignum-vitae/goombay
Project-URL: Issues, https://github.com/lignum-vitae/goombay/issues
Author-email: Andrew Hennis <andrew.mr.hennis@gmail.com>
License-File: LICENSE
Classifier: License :: OSI Approved :: MIT License
Classifier: Operating System :: OS Independent
Classifier: Programming Language :: Python :: 3
Requires-Python: >=3.10
Requires-Dist: biobase>=0.8.0
Requires-Dist: biopython>=1.85
Requires-Dist: numpy>=2.2.6
Provides-Extra: dev
Requires-Dist: black; extra == 'dev'
Requires-Dist: pytest; extra == 'dev'
